sqliscan/__init__.py
sqliscan/main.py
sqliscan/includes/__init__.py
sqliscan/includes/filereader.py
sqliscan/includes/scan.py
sqliscan/utils/__init__.py
sqliscan/utils/const.py
sqliscan/utils/helpers.py
sqliscan-1.2.dist-info/METADATA
sqliscan-1.2.dist-info/WHEEL
sqliscan-1.2.dist-info/entry_points.txt
sqliscan-1.2.dist-info/top_level.txt
sqliscan-1.2.dist-info/RECORD
