Metadata-Version: 2.1
Name: sqliscan
Version: 1.2
Home-page: https://github.com/mdaseem03/
Requires-Dist: click
Requires-Dist: requests
Requires-Dist: beautifulsoup4
